CompStats/__init__.py
CompStats/bootstrap.py
CompStats/interface.py
CompStats/measurements.py
CompStats/metrics.py
CompStats/performance.py
CompStats/utils.py
CompStats/tests/__init__.py
CompStats/tests/data.csv
CompStats/tests/test_bootstrap.py
CompStats/tests/test_interface.py
CompStats/tests/test_measurements.py
CompStats/tests/test_metrics.py
CompStats/tests/test_performance.py
compstats-0.1.13.dist-info/licenses/LICENSE
compstats-0.1.13.dist-info/METADATA
compstats-0.1.13.dist-info/WHEEL
compstats-0.1.13.dist-info/top_level.txt
compstats-0.1.13.dist-info/RECORD
