Metadata-Version: 2.4
Name: CompStats
Version: 0.1.13
Summary: CompStats implements an evaluation methodology for statistically analyzing competition results and competition
Project-URL: Homepage, https://compstats.readthedocs.io
Project-URL: Repository, https://github.com/INGEOTEC/CompStats
Project-URL: Issues, https://github.com/INGEOTEC/CompStats/issues
Classifier: Development Status :: 4 - Beta
Classifier: Environment :: Console
Classifier: Intended Audience :: Developers
Classifier: Intended Audience :: Information Technology
Classifier: Intended Audience :: Science/Research
Classifier: License :: OSI Approved :: MIT License
Classifier: Operating System :: OS Independent
Classifier: Programming Language :: Python
Classifier: Topic :: Scientific/Engineering :: Artificial Intelligence
Classifier: Topic :: Scientific/Engineering :: Information Analysis
License-File: LICENSE
Requires-Dist: numpy
Requires-Dist: scikit-learn>=1.3.0
Requires-Dist: pandas
Requires-Dist: seaborn>=0.13.0
Requires-Dist: statsmodels
Dynamic: license-file
